jiajia/__init__.py
jiajia/config.py
jiajia/encryption_api.py
jiajia/encryption_core.py
jiajia/session_manager.py
jiajia/utils.py
jiajia-1.1.0.dist-info/LICENSE
jiajia-1.1.0.dist-info/METADATA
jiajia-1.1.0.dist-info/WHEEL
jiajia-1.1.0.dist-info/top_level.txt
jiajia-1.1.0.dist-info/RECORD
