Metadata-Version: 2.1
Name: jiajia
Version: 1.1.0
Summary: 轻量级RSA-AES混合加密框架
Home-page: https://github.com/xiatian/jiajia
Author: 夏云龙
Author-email: 夏云龙 <1900098962@qq.com>
Maintainer-email: 夏云龙 <1900098962@qq.com>
License: MIT
Project-URL: Homepage, https://github.com/xiatian/jiajia
Project-URL: Repository, https://github.com/xiatian/jiajia
Project-URL: Documentation, https://github.com/xiatian/jiajia#readme
Project-URL: Issues, https://github.com/xiatian/jiajia/issues
Keywords: encryption,cryptography,rsa,aes,hmac,security,hybrid
Classifier: Development Status :: 4 - Beta
Classifier: Intended Audience :: Developers
Classifier: License :: OSI Approved :: MIT License
Classifier: Operating System :: OS Independent
Classifier: Programming Language :: Python :: 3
Classifier: Programming Language :: Python :: 3.8
Classifier: Programming Language :: Python :: 3.9
Classifier: Programming Language :: Python :: 3.10
Classifier: Programming Language :: Python :: 3.11
Classifier: Programming Language :: Python :: 3.12
Classifier: Topic :: Security :: Cryptography
Classifier: Topic :: Software Development :: Libraries :: Python Modules
Requires-Python: >=3.8
License-File: LICENSE
Requires-Dist: cryptography>=3.4.0
Provides-Extra: dev
Requires-Dist: pytest>=6.0.0; extra == "dev"
Requires-Dist: pytest-asyncio>=0.18.0; extra == "dev"
Requires-Dist: black>=21.0.0; extra == "dev"
Requires-Dist: flake8>=3.8.0; extra == "dev"
Provides-Extra: redis
Requires-Dist: redis>=4.0.0; extra == "redis"
